{
  "url": "http://127.0.0.1:5173/intro",
  "timestamp": 1760490000515,
  "lcp": 0,
  "fcp": 1761,
  "cls": 0,
  "navigation": {
    "name": "http://127.0.0.1:5173/",
    "entryType": "navigation",
    "startTime": 0,
    "duration": 1587,
    "initiatorType": "navigation",
    "nextHopProtocol": "http/1.1",
    "workerStart": 0,
    "redirectStart": 0,
    "redirectEnd": 0,
    "fetchStart": -7,
    "domainLookupStart": 89,
    "domainLookupEnd": 89,
    "connectStart": 89,
    "connectEnd": 90,
    "secureConnectionStart": 0,
    "requestStart": 90,
    "responseStart": 98,
    "responseEnd": 98,
    "transferSize": 3714,
    "encodedBodySize": 3414,
    "decodedBodySize": 3414,
    "responseStatus": 200,
    "contentType": "text/html",
    "serverTiming": [],
    "unloadEventStart": 0,
    "unloadEventEnd": 0,
    "domInteractive": 141,
    "domContentLoadedEventStart": 1226,
    "domContentLoadedEventEnd": 1228,
    "domComplete": 1587,
    "loadEventStart": 1587,
    "loadEventEnd": 1587,
    "type": "navigate",
    "redirectCount": 0
  },
  "paints": [
    {
      "name": "first-contentful-paint",
      "startTime": 1761
    }
  ],
  "entries": {
    "lcp": [],
    "cls": [],
    "fcp": [
      {
        "name": "first-contentful-paint",
        "entryType": "paint",
        "startTime": 1761,
        "duration": 0,
        "paintTime": 1761,
        "presentationTime": null
      }
    ]
  },
  "userAgent": "Mozilla/5.0 (Windows NT 10.0; Win64; x64; rv:142.0.1) Gecko/20100101 Firefox/142.0.1"
}